CloseableQueue.py
CloseableQueue/test/__init__.py
CloseableQueue/test/test_queue.py
CloseableQueue/test/test_support.py
CloseableQueue_py3-0.9.2.dist-info/COPYING
CloseableQueue_py3-0.9.2.dist-info/METADATA
CloseableQueue_py3-0.9.2.dist-info/WHEEL
CloseableQueue_py3-0.9.2.dist-info/top_level.txt
CloseableQueue_py3-0.9.2.dist-info/RECORD
