Metadata-Version: 2.1
Name: CloseableQueue-py3
Version: 0.9.2
Summary: These classes and functions provide the facility to close a queue and to use it as an iterator.
Home-page: https://github.com/ejd/CloseableQueue
Author: Ted Tibbetts
Author-email: intuited@gmail.com
Maintainer: Eric Dramstad
Maintainer-email: edrams@gmail.com
License: UNKNOWN
Keywords: queue,multithreading,threading,iterator,iterable,iteration
Platform: UNKNOWN
Classifier: Development Status :: 4 - Beta
Classifier: Intended Audience :: Developers
Classifier: License :: OSI Approved :: BSD License
Classifier: Operating System :: OS Independent
Classifier: Programming Language :: Python
Classifier: Programming Language :: Python :: 2
Classifier: Programming Language :: Python :: 3
Classifier: Topic :: Software Development :: Libraries :: Python Modules
Classifier: Topic :: Utilities
